flask_graylog.py
Flask_Graylog2-1.2.2.dist-info/LICENSE
Flask_Graylog2-1.2.2.dist-info/WHEEL
Flask_Graylog2-1.2.2.dist-info/METADATA
Flask_Graylog2-1.2.2.dist-info/RECORD
