Metadata-Version: 2.1
Name: Flask-Graylog2
Version: 1.2.2
Summary: Configure Graylog logging handlers and middleware for your Flask app.
Home-page: https://github.com/gridscale/flask-graylog2
License: UNKNOWN
Author: gridscale GmbH
Author-email: team@gridscale.io
Maintainer: Benjamin Kircher
Maintainer-email: bkircher@gridscale.io
Requires-Python: >=3.5
Classifier: Environment :: Web Environment
Classifier: Intended Audience :: Developers
Classifier: License :: OSI Approved :: MIT License
Classifier: Operating System :: OS Independent
Classifier: Programming Language :: Python
Classifier: Topic :: Software Development :: Libraries :: Python Modules
Requires-Dist: Flask
Requires-Dist: graypy
